parq2csv/__init__.py
parq2csv/main.py
parq2csv-0.1.3.dist-info/LICENSE
parq2csv-0.1.3.dist-info/METADATA
parq2csv-0.1.3.dist-info/WHEEL
parq2csv-0.1.3.dist-info/entry_points.txt
parq2csv-0.1.3.dist-info/top_level.txt
parq2csv-0.1.3.dist-info/RECORD
