Metadata-Version: 2.1
Name: parq2csv
Version: 0.1.3
Summary: Command line tool to transform Apache Parquet files to CSV on the go
Home-page: https://github.com/mludv/parq2csv
Author: Maximilian Ludvigsson
Author-email: maxiludvigsson@gmail.com
License: UNKNOWN
Platform: any
Classifier: Intended Audience :: Developers
Classifier: Programming Language :: Python
Classifier: Programming Language :: Python :: 3
Requires-Dist: pandas (>=0.22.0)
Requires-Dist: pyarrow (>=0.11.0)
